pinnies/__init__.py
pinnies/base.py
pinnies/fractinoal.py
pinnies/fredholm.py
pinnies/ie.py
pinnies/utils.py
pinnies/volterra.py
pinnies-0.0.1.dist-info/LICENSE
pinnies-0.0.1.dist-info/METADATA
pinnies-0.0.1.dist-info/WHEEL
pinnies-0.0.1.dist-info/top_level.txt
pinnies-0.0.1.dist-info/RECORD
