Metadata-Version: 2.1
Name: pinnies
Version: 0.0.1
Summary: A Physics-Informed Neural Network Framework for Solving Integral Equations
Home-page: https://github.com/alirezaafzalaghaei/pinnies
Author: Alireza Afzal Aghaei
Author-email: alirezaafzalaghaei@gmail.com
License: BSD
License-File: LICENSE
Requires-Dist: torch
Requires-Dist: tqdm
Requires-Dist: scipy
Requires-Dist: numpy
